<annotation>
	<folder>my-project-name</folder>
	<filename>piktogramm-00079.jpg</filename>
	<path>/my-project-name/piktogramm-00079.jpg</path>
	<source>
		<database>Unspecified</database>
	</source>
	<size>
		<width>1920</width>
		<height>1088</height>
		<depth>3</depth>
	</size>
	<object>
		<name>taco</name>
		<pose>Unspecified</pose>
		<truncated>Unspecified</truncated>
		<difficult>Unspecified</difficult>
		<bndbox>
			<xmin>544</xmin>
			<ymin>292</ymin>
			<xmax>980</xmax>
			<ymax>706</ymax>
		</bndbox>
	</object>
	<object>
		<name>brick</name>
		<pose>Unspecified</pose>
		<truncated>Unspecified</truncated>
		<difficult>Unspecified</difficult>
		<bndbox>
			<xmin>1622</xmin>
			<ymin>429</ymin>
			<xmax>1738</xmax>
			<ymax>468</ymax>
		</bndbox>
	</object>
	<object>
		<name>brick</name>
		<pose>Unspecified</pose>
		<truncated>Unspecified</truncated>
		<difficult>Unspecified</difficult>
		<bndbox>
			<xmin>1658</xmin>
			<ymin>310</ymin>
			<xmax>1819</xmax>
			<ymax>349</ymax>
		</bndbox>
	</object>
	<object>
		<name>brick</name>
		<pose>Unspecified</pose>
		<truncated>Unspecified</truncated>
		<difficult>Unspecified</difficult>
		<bndbox>
			<xmin>1742</xmin>
			<ymin>209</ymin>
			<xmax>1889</xmax>
			<ymax>246</ymax>
		</bndbox>
	</object>
	<object>
		<name>brick</name>
		<pose>Unspecified</pose>
		<truncated>Unspecified</truncated>
		<difficult>Unspecified</difficult>
		<bndbox>
			<xmin>1596</xmin>
			<ymin>140</ymin>
			<xmax>1731</xmax>
			<ymax>170</ymax>
		</bndbox>
	</object>
	<object>
		<name>brick</name>
		<pose>Unspecified</pose>
		<truncated>Unspecified</truncated>
		<difficult>Unspecified</difficult>
		<bndbox>
			<xmin>1576</xmin>
			<ymin>38</ymin>
			<xmax>1647</xmax>
			<ymax>100</ymax>
		</bndbox>
	</object>
</annotation>