<annotation>
	<folder>my-project-name</folder>
	<filename>piktogramm-00274.jpg</filename>
	<path>/my-project-name/piktogramm-00274.jpg</path>
	<source>
		<database>Unspecified</database>
	</source>
	<size>
		<width>1920</width>
		<height>1088</height>
		<depth>3</depth>
	</size>
	<object>
		<name>taco</name>
		<pose>Unspecified</pose>
		<truncated>Unspecified</truncated>
		<difficult>Unspecified</difficult>
		<bndbox>
			<xmin>650</xmin>
			<ymin>293</ymin>
			<xmax>1085</xmax>
			<ymax>731</ymax>
		</bndbox>
	</object>
	<object>
		<name>brick</name>
		<pose>Unspecified</pose>
		<truncated>Unspecified</truncated>
		<difficult>Unspecified</difficult>
		<bndbox>
			<xmin>438</xmin>
			<ymin>542</ymin>
			<xmax>527</xmax>
			<ymax>581</ymax>
		</bndbox>
	</object>
	<object>
		<name>brick</name>
		<pose>Unspecified</pose>
		<truncated>Unspecified</truncated>
		<difficult>Unspecified</difficult>
		<bndbox>
			<xmin>422</xmin>
			<ymin>430</ymin>
			<xmax>525</xmax>
			<ymax>469</ymax>
		</bndbox>
	</object>
	<object>
		<name>brick</name>
		<pose>Unspecified</pose>
		<truncated>Unspecified</truncated>
		<difficult>Unspecified</difficult>
		<bndbox>
			<xmin>472</xmin>
			<ymin>348</ymin>
			<xmax>521</xmax>
			<ymax>379</ymax>
		</bndbox>
	</object>
</annotation>