<annotation>
	<folder>my-project-name</folder>
	<filename>piktogramm-5-00088.jpg</filename>
	<path>/my-project-name/piktogramm-5-00088.jpg</path>
	<source>
		<database>Unspecified</database>
	</source>
	<size>
		<width>1920</width>
		<height>1088</height>
		<depth>3</depth>
	</size>
	<object>
		<name>hammer</name>
		<pose>Unspecified</pose>
		<truncated>Unspecified</truncated>
		<difficult>Unspecified</difficult>
		<bndbox>
			<xmin>549</xmin>
			<ymin>249</ymin>
			<xmax>1004</xmax>
			<ymax>715</ymax>
		</bndbox>
	</object>
	<object>
		<name>brick</name>
		<pose>Unspecified</pose>
		<truncated>Unspecified</truncated>
		<difficult>Unspecified</difficult>
		<bndbox>
			<xmin>1532</xmin>
			<ymin>415</ymin>
			<xmax>1641</xmax>
			<ymax>458</ymax>
		</bndbox>
	</object>
	<object>
		<name>brick</name>
		<pose>Unspecified</pose>
		<truncated>Unspecified</truncated>
		<difficult>Unspecified</difficult>
		<bndbox>
			<xmin>1554</xmin>
			<ymin>301</ymin>
			<xmax>1706</xmax>
			<ymax>338</ymax>
		</bndbox>
	</object>
	<object>
		<name>brick</name>
		<pose>Unspecified</pose>
		<truncated>Unspecified</truncated>
		<difficult>Unspecified</difficult>
		<bndbox>
			<xmin>1625</xmin>
			<ymin>201</ymin>
			<xmax>1769</xmax>
			<ymax>242</ymax>
		</bndbox>
	</object>
	<object>
		<name>brick</name>
		<pose>Unspecified</pose>
		<truncated>Unspecified</truncated>
		<difficult>Unspecified</difficult>
		<bndbox>
			<xmin>1512</xmin>
			<ymin>133</ymin>
			<xmax>1610</xmax>
			<ymax>164</ymax>
		</bndbox>
	</object>
	<object>
		<name>brick</name>
		<pose>Unspecified</pose>
		<truncated>Unspecified</truncated>
		<difficult>Unspecified</difficult>
		<bndbox>
			<xmin>1487</xmin>
			<ymin>38</ymin>
			<xmax>1527</xmax>
			<ymax>89</ymax>
		</bndbox>
	</object>
</annotation>